crazyweirdpackage/__init__.py
crazyweirdpackage/setup.py
crazyweirdpackage-0.0.1.dist-info/METADATA
crazyweirdpackage-0.0.1.dist-info/WHEEL
crazyweirdpackage-0.0.1.dist-info/top_level.txt
crazyweirdpackage-0.0.1.dist-info/RECORD
